{
    "questions": [
      {
        "theme": "Personal Reflection",
        "question": "What were my three happiest moments this year?",
        "type": "open-ended"
      },
      {
        "theme": "Personal Reflection",
        "question": "Which personal qualities have I developed most?",
        "type": "open-ended"
      },
      {
        "theme": "Personal Reflection",
        "question": "What was the biggest challenge I overcame?",
        "type": "open-ended"
      },
      {
        "theme": "Personal Reflection",
        "question": "Who positively influenced my life the most and how?",
        "type": "open-ended"
      },
      {
        "theme": "Personal Reflection",
        "question": "What are three things I did this year that I'm proud of?",
        "type": "open-ended"
      },
      {
        "theme": "Personal Reflection",
        "question": "What was the most important lesson I learned about myself?",
        "type": "open-ended"
      },
      {
        "theme": "Personal Reflection",
        "question": "What new interests or hobbies did I discover?",
        "type": "open-ended"
      },
      {
        "theme": "Personal Reflection",
        "question": "In what ways did I grow emotionally and spiritually?",
        "type": "open-ended"
      },
      {
        "theme": "Personal Reflection",
        "question": "What am I most grateful for from this year?",
        "type": "open-ended"
      },
      {
        "theme": "Personal Reflection",
        "question": "How have my relationships evolved or changed?",
        "type": "open-ended"
      },
      {
        "theme": "Career Reflection",
        "question": "What professional achievements am I most proud of this year?",
        "type": "open-ended"
      },
      {
        "theme": "Career Reflection",
        "question": "What new skills or knowledge did I acquire?",
        "type": "open-ended"
      },
      {
        "theme": "Career Reflection",
        "question": "What was the most significant challenge at work and how did I handle it?",
        "type": "open-ended"
      },
      {
        "theme": "Career Reflection",
        "question": "How has my career path shifted or progressed?",
        "type": "open-ended"
      },
      {
        "theme": "Career Reflection",
        "question": "What feedback have I received and how have I implemented it?",
        "type": "open-ended"
      },
      {
        "theme": "Career Reflection",
        "question": "In what ways did I contribute to my team or company?",
        "type": "open-ended"
      },
      {
        "theme": "Career Reflection",
        "question": "What networking or professional relationships did I develop?",
        "type": "open-ended"
      },
      {
        "theme": "Career Reflection",
        "question": "How did I balance work with personal life?",
        "type": "open-ended"
      },
      {
        "theme": "Career Reflection",
        "question": "What are my career goals for the next year?",
        "type": "open-ended"
      },
      {
        "theme": "Career Reflection",
        "question": "What professional habits do I want to develop or change?",
        "type": "open-ended"
      },
      {
        "theme": "Health and Wellbeing",
        "question": "How did I prioritize my physical health this year?",
        "type": "open-ended"
      },
      {
        "theme": "Health and Wellbeing",
        "question": "What healthy habits did I adopt or continue?",
        "type": "open-ended"
      },
      {
        "theme": "Health and Wellbeing",
        "question": "How did I manage stress and maintain mental health?",
        "type": "open-ended"
      },
      {
        "theme": "Health and Wellbeing",
        "question": "In what ways did I prioritize self-care?",
        "type": "open-ended"
      },
      {
        "theme": "Health and Wellbeing",
        "question": "What steps did I take towards a healthier lifestyle?",
        "type": "open-ended"
      },
      {
        "theme": "Personal Values and Beliefs",
        "question": "How have my values and beliefs guided my decisions?",
        "type": "open-ended"
      },
      {
        "theme": "Personal Values and Beliefs",
        "question": "What causes or issues am I passionate about?",
        "type": "open-ended"
      },
      {
        "theme": "Personal Values and Beliefs",
        "question": "In what ways have I contributed to the community or world?",
        "type": "open-ended"
      },
      {
        "theme": "Personal Values and Beliefs",
        "question": "Have my priorities shifted this year? If so, how?",
        "type": "open-ended"
      },
      {
        "theme": "Personal Values and Beliefs",
        "question": "What are the core values that I want to live by?",
        "type": "open-ended"
      },
      {
        "theme": "Future Planning and Goals",
        "question": "What are my personal goals for the next year?",
        "type": "open-ended"
      },
      {
        "theme": "Future Planning and Goals",
        "question": "How do I envision my career a year from now?",
        "type": "open-ended"
      },
      {
        "theme": "Future Planning and Goals",
        "question": "What steps can I take to achieve my goals?",
        "type": "open-ended"
      },
      {
        "theme": "Future Planning and Goals",
        "question": "Who can support me in my future endeavors?",
        "type": "open-ended"
      },
      {
        "theme": "Future Planning and Goals",
        "question": "What are potential obstacles and how can I overcome them?",
        "type": "open-ended"
      },
      {
        "theme": "Lifestyle and Experiences",
        "question": "What new experiences did I have this year?",
        "type": "open-ended"
      },
      {
        "theme": "Lifestyle and Experiences",
        "question": "How have I stepped out of my comfort zone?",
        "type": "open-ended"
      },
      {
        "theme": "Lifestyle and Experiences",
        "question": "In what ways did I invest in my personal growth?",
        "type": "open-ended"
      },
      {
        "theme": "Lifestyle and Experiences",
        "question": "What are three things I'd like to learn next year?",
        "type": "open-ended"
      },
      {
        "theme": "Lifestyle and Experiences",
        "question": "How can I make my daily life more fulfilling?",
        "type": "open-ended"
      },
      {
        "theme": "Self-Expression and Creativity",
        "question": "How have I expressed myself creatively?",
        "type": "open-ended"
      },
      {
        "theme": "Self-Expression and Creativity",
        "question": "What projects or creative endeavors brought me joy?",
        "type": "open-ended"
      },
      {
        "theme": "Self-Expression and Creativity",
        "question": "How can I incorporate more creativity into my life?",
        "type": "open-ended"
      },
      {
        "theme": "Self-Expression and Creativity",
        "question": "What forms of self-expression do I want to explore?",
        "type": "open-ended"
      },
      {
        "theme": "Self-Expression and Creativity",
        "question": "How has my personal style or expression evolved?",
        "type": "open-ended"
      },
      {
        "theme": "Mindset and Attitude",
        "question": "What mindset shifts have been most beneficial?",
        "type": "open-ended"
      },
      {
        "theme": "Mindset and Attitude",
        "question": "How do I handle setbacks and failures?",
        "type": "open-ended"
      },
      {
        "theme": "Mindset and Attitude",
        "question": "What are my attitudes towards change and growth?",
        "type": "open-ended"
      },
      {
        "theme": "Mindset and Attitude",
        "question": "How can I cultivate a more positive outlook?",
        "type": "open-ended"
      },
      {
        "theme": "Mindset and Attitude",
        "question": "What beliefs do I need to challenge or reassess?",
        "type": "open-ended"
      },
      {
        "theme": "Personal Development and Self-Reflection",
        "question": "I feel satisfied with the personal growth I achieved this year.",
        "type": "likert",
        "scale": "Strongly Disagree to Strongly Agree"
      },
      {
        "theme": "Personal Development and Self-Reflection",
        "question": "I effectively managed stress and maintained a positive mindset.",
        "type": "likert",
        "scale": "Strongly Disagree to Strongly Agree"
      },
      {
        "theme": "Personal Development and Self-Reflection",
        "question": "I often stepped out of my comfort zone to try new things.",
        "type": "likert",
        "scale": "Strongly Disagree to Strongly Agree"
      },
    {
        "theme": "Personal Development and Self-Reflection",
        "question": "I feel satisfied with the personal growth I achieved this year.",
        "type": "likert",
        "scale": "Strongly Disagree to Strongly Agree"
    },
    {
        "theme": "Personal Development and Self-Reflection",
        "question": "I effectively managed stress and maintained a positive mindset.",
        "type": "likert",
        "scale": "Strongly Disagree to Strongly Agree"
    },
    {
        "theme": "Personal Development and Self-Reflection",
        "question": "I often stepped out of my comfort zone to try new things.",
        "type": "likert",
        "scale": "Strongly Disagree to Strongly Agree"
    },
    {
        "theme": "Personal Development and Self-Reflection",
        "question": "I maintained a healthy balance between work and personal life.",
        "type": "likert",
        "scale": "Strongly Disagree to Strongly Agree"
    },
    {
        "theme": "Personal Development and Self-Reflection",
        "question": "I regularly practiced self-care and prioritized my well-being.",
        "type": "likert",
        "scale": "Strongly Disagree to Strongly Agree"
    },
    {
        "theme": "Career and Professional Growth",
        "question": "I am satisfied with my career progress over the past year.",
        "type": "likert",
        "scale": "Strongly Disagree to Strongly Agree"
    },
    {
        "theme": "Career and Professional Growth",
        "question": "I feel that I have a clear direction in my career path.",
        "type": "likert",
        "scale": "Strongly Disagree to Strongly Agree"
    },
    {
        "theme": "Career and Professional Growth",
        "question": "I believe that I have developed significant professional skills.",
        "type": "likert",
        "scale": "Strongly Disagree to Strongly Agree"
    },
    {
        "theme": "Career and Professional Growth",
        "question": "I effectively balanced my professional responsibilities and personal life.",
        "type": "likert",
        "scale": "Strongly Disagree to Strongly Agree"
    },
    {
        "theme": "Career and Professional Growth",
        "question": "I feel confident in my ability to overcome professional challenges.",
        "type": "likert",
        "scale": "Strongly Disagree to Strongly Agree"
    },
    {
        "theme": "Relationships and Social Connections",
        "question": "I am satisfied with the quality of my relationships.",
        "type": "likert",
        "scale": "Strongly Disagree to Strongly Agree"
    },
    {
        "theme": "Relationships and Social Connections",
        "question": "I feel supported by my friends and family.",
        "type": "likert",
        "scale": "Strongly Disagree to Strongly Agree"
    },
    {
        "theme": "Relationships and Social Connections",
        "question": "I effectively communicated my needs and boundaries in relationships.",
        "type": "likert",
        "scale": "Strongly Disagree to Strongly Agree"
    },
    {
        "theme": "Relationships and Social Connections",
        "question": "I made meaningful new connections this year.",
        "type": "likert",
        "scale": "Strongly Disagree to Strongly Agree"
    },
    {
        "theme": "Relationships and Social Connections",
        "question": "I contributed positively to the lives of others around me.",
        "type": "likert",
        "scale": "Strongly Disagree to Strongly Agree"
    },
    {
        "theme": "Health and Wellness",
        "question": "I am satisfied with my physical health and fitness level.",
        "type": "likert",
        "scale": "Strongly Disagree to Strongly Agree"
    },
    {
        "theme": "Health and Wellness",
        "question": "I regularly engaged in physical activities that I enjoy.",
        "type": "likert",
        "scale": "Strongly Disagree to Strongly Agree"
    },
    {
        "theme": "Health and Wellness",
        "question": "I maintained a healthy diet and lifestyle throughout the year.",
        "type": "likert",
        "scale": "Strongly Disagree to Strongly Agree"
    },
    {
        "theme": "Health and Wellness",
        "question": "I successfully managed stress through healthy coping mechanisms.",
        "type": "likert",
        "scale": "Strongly Disagree to Strongly Agree"
    },
    {
        "theme": "Health and Wellness",
        "question": "I feel energetic and well-rested most of the time.",
        "type": "likert",
        "scale": "Strongly Disagree to Strongly Agree"
    },
    {
        "theme": "Personal Interests and Hobbies",
        "question": "I spent adequate time on hobbies and activities I enjoy.",
        "type": "likert",
        "scale": "Strongly Disagree to Strongly Agree"
    },
    {
        "theme": "Personal Interests and Hobbies",
        "question": "I explored new interests that enriched my life.",
        "type": "likert",
        "scale": "Strongly Disagree to Strongly Agree"
    },
    {
        "theme": "Personal Interests and Hobbies",
        "question": "I feel creatively fulfilled.",
        "type": "likert",
        "scale": "Strongly Disagree to Strongly Agree"
    },
    {
        "theme": "Personal Interests and Hobbies",
        "question": "My hobbies and interests provided a good break from work.",
        "type": "likert",
        "scale": "Strongly Disagree to Strongly Agree"
    },
    {
        "theme": "Personal Interests and Hobbies",
        "question": "I shared my hobbies and interests with others.",
        "type": "likert",
        "scale": "Strongly Disagree to Strongly Agree"
    },
    {
        "theme": "Financial Management",
        "question": "I am satisfied with my financial management this year.",
        "type": "likert",
        "scale": "Strongly Disagree to Strongly Agree"
    },
    {
        "theme": "Financial Management",
        "question": "I made progress towards my financial goals.",
        "type": "likert",
        "scale": "Strongly Disagree to Strongly Agree"
    },
    {
        "theme": "Financial Management",
        "question": "I feel confident about my financial future.",
        "type": "likert",
        "scale": "Strongly Disagree to Strongly Agree"
    },
    {
        "theme": "Financial Management",
        "question": "I effectively balanced saving with enjoying my earnings.",
        "type": "likert",
        "scale": "Strongly Disagree to Strongly Agree"
    },
    {
        "theme": "Financial Management",
        "question": "I educated myself about financial planning and investments.",
        "type": "likert",
        "scale": "Strongly Disagree to Strongly Agree"
    },
    {
        "theme": "Emotional Wellbeing",
        "question": "I feel emotionally balanced and stable.",
        "type": "likert",
        "scale": "Strongly Disagree to Strongly Agree"
    },
    {
        "theme": "Emotional Wellbeing",
        "question": "I effectively expressed my emotions in a healthy way.",
        "type": "likert",
        "scale": "Strongly Disagree to Strongly Agree"
    },
    {
        "theme": "Emotional Wellbeing",
        "question": "I sought support when dealing with difficult emotions.",
        "type": "likert",
        "scale": "Strongly Disagree to Strongly Agree"
    },
    {
        "theme": "Emotional Wellbeing",
        "question": "I feel content with my life.",
        "type": "likert",
        "scale": "Strongly Disagree to Strongly Agree"
    },
    {
        "theme": "Emotional Wellbeing",
        "question": "I regularly practiced activities that promote emotional wellbeing.",
        "type": "likert",
        "scale": "Strongly Disagree to Strongly Agree"
    }      
    ]
}
      
       
  